[
  {
    "id": "https://www.competitions.co.nz/win-wallace-cotton-heirloom-sheet-pillowcase-set/37754",
    "title": "Win a Wallace Cotton Heirloom Sheet and Pillowcase Set",
    "link": "https://www.competitions.co.nz/win-wallace-cotton-heirloom-sheet-pillowcase-set/37754",
    "source": "Competitions.co.nz",
    "createdAt": "2025-11-11T03:41:55.479Z",
    "deadline": null,
    "tags": []
  },
  {
    "id": "https://www.competitions.co.nz/win-roomba-max-705-combo-robot-autowash-dock/37753",
    "title": "Win a Roomba Max 705 Combo Robot & Autowash Dock",
    "link": "https://www.competitions.co.nz/win-roomba-max-705-combo-robot-autowash-dock/37753",
    "source": "Competitions.co.nz",
    "createdAt": "2025-11-11T03:41:55.479Z",
    "deadline": null,
    "tags": []
  },
  {
    "id": "https://www.competitions.co.nz/win-prizes/37752",
    "title": "Win $730 in Prizes",
    "link": "https://www.competitions.co.nz/win-prizes/37752",
    "source": "Competitions.co.nz",
    "createdAt": "2025-11-11T03:41:55.479Z",
    "deadline": null,
    "tags": []
  },
  {
    "id": "https://www.competitions.co.nz/win-mystery-box-packed-mystical-potions-lotions/37751",
    "title": "Win a Mystery Box Packed with Mystical Potions and Lotions",
    "link": "https://www.competitions.co.nz/win-mystery-box-packed-mystical-potions-lotions/37751",
    "source": "Competitions.co.nz",
    "createdAt": "2025-11-11T03:41:55.479Z",
    "deadline": null,
    "tags": []
  },
  {
    "id": "https://www.competitions.co.nz/win-5k-sarah-sebastian-petite-tennis-bracelet/37750",
    "title": "Win a $9.5K Sarah & Sebastian Petite Tennis Bracelet",
    "link": "https://www.competitions.co.nz/win-5k-sarah-sebastian-petite-tennis-bracelet/37750",
    "source": "Competitions.co.nz",
    "createdAt": "2025-11-11T03:41:55.479Z",
    "deadline": null,
    "tags": []
  },
  {
    "id": "https://www.competitions.co.nz/win-linden-leaves-amber-fig-hands-home-gift-set/37748",
    "title": "Win a Linden Leaves Amber Fig Hands & Home Gift Set",
    "link": "https://www.competitions.co.nz/win-linden-leaves-amber-fig-hands-home-gift-set/37748",
    "source": "Competitions.co.nz",
    "createdAt": "2025-11-11T03:41:55.479Z",
    "deadline": null,
    "tags": []
  },
  {
    "id": "https://www.competitions.co.nz/win-kas-australia-gift-voucher/37747",
    "title": "Win a $2K KAS Australia Gift Voucher",
    "link": "https://www.competitions.co.nz/win-kas-australia-gift-voucher/37747",
    "source": "Competitions.co.nz",
    "createdAt": "2025-11-11T03:41:55.479Z",
    "deadline": null,
    "tags": []
  },
  {
    "id": "https://www.competitions.co.nz/win-years-supply-jack-links-beef-biltong/37746",
    "title": "Win a Year's Supply of JACK Link's BEEF Biltong",
    "link": "https://www.competitions.co.nz/win-years-supply-jack-links-beef-biltong/37746",
    "source": "Competitions.co.nz",
    "createdAt": "2025-11-11T03:41:55.479Z",
    "deadline": null,
    "tags": []
  },
  {
    "id": "https://www.competitions.co.nz/win-vip-weekend-at-coachella/37745",
    "title": "Win a VIP Weekend at Coachella",
    "link": "https://www.competitions.co.nz/win-vip-weekend-at-coachella/37745",
    "source": "Competitions.co.nz",
    "createdAt": "2025-11-11T03:41:55.479Z",
    "deadline": "2025-12-01T00:00:00.000Z",
    "tags": []
  },
  {
    "id": "https://www.competitions.co.nz/win-gift-card/37742",
    "title": "Win a $500 Gift Card",
    "link": "https://www.competitions.co.nz/win-gift-card/37742",
    "source": "Competitions.co.nz",
    "createdAt": "2025-11-11T03:41:55.479Z",
    "deadline": null,
    "tags": []
  },
  {
    "id": "https://www.competitions.co.nz/win-400ct-natural-diamond-14ct-white-gold-tennis-bracelet/37738",
    "title": "Win a 4.00ct Natural Diamond 14ct White Gold Tennis Bracelet",
    "link": "https://www.competitions.co.nz/win-400ct-natural-diamond-14ct-white-gold-tennis-bracelet/37738",
    "source": "Competitions.co.nz",
    "createdAt": "2025-11-11T03:41:55.479Z",
    "deadline": null,
    "tags": []
  },
  {
    "id": "https://www.competitions.co.nz/win-petite-vault-limited-edition/37736",
    "title": "Win the Petite Vault Limited Edition",
    "link": "https://www.competitions.co.nz/win-petite-vault-limited-edition/37736",
    "source": "Competitions.co.nz",
    "createdAt": "2025-11-11T03:41:55.479Z",
    "deadline": "2025-11-14T00:00:00.000Z",
    "tags": []
  },
  {
    "id": "https://www.competitions.co.nz/win-yamaha-drum-kit/37732",
    "title": "Win a Yamaha Drum Kit",
    "link": "https://www.competitions.co.nz/win-yamaha-drum-kit/37732",
    "source": "Competitions.co.nz",
    "createdAt": "2025-11-11T03:41:55.479Z",
    "deadline": null,
    "tags": []
  },
  {
    "id": "https://www.competitions.co.nz/win-gift-voucher-every-month/37730",
    "title": "Win a $500 Gift Voucher Every Month",
    "link": "https://www.competitions.co.nz/win-gift-voucher-every-month/37730",
    "source": "Competitions.co.nz",
    "createdAt": "2025-11-11T03:41:55.479Z",
    "deadline": "2025-12-31T00:00:00.000Z",
    "tags": []
  },
  {
    "id": "https://www.competitions.co.nz/win-travel-voucher-arlon-tool-prize-pack/37727",
    "title": "Win a $500 Travel Voucher & Arlon Tool Prize Pack",
    "link": "https://www.competitions.co.nz/win-travel-voucher-arlon-tool-prize-pack/37727",
    "source": "Competitions.co.nz",
    "createdAt": "2025-11-11T03:41:55.479Z",
    "deadline": "2025-12-01T00:00:00.000Z",
    "tags": []
  },
  {
    "id": "https://www.competitions.co.nz/win-prizes/37726",
    "title": "Win a Share $25K in Prizes",
    "link": "https://www.competitions.co.nz/win-prizes/37726",
    "source": "Competitions.co.nz",
    "createdAt": "2025-11-11T03:41:55.479Z",
    "deadline": null,
    "tags": []
  },
  {
    "id": "https://www.competitions.co.nz/win-lego-retro-movie-bundle/37723",
    "title": "Win a LEGO® Retro Movie Bundle",
    "link": "https://www.competitions.co.nz/win-lego-retro-movie-bundle/37723",
    "source": "Competitions.co.nz",
    "createdAt": "2025-11-11T03:41:55.479Z",
    "deadline": null,
    "tags": []
  },
  {
    "id": "https://www.competitions.co.nz/win-all-inclusive-asia-exploration-cruise/37721",
    "title": "Win an all-Inclusive Asia Exploration Cruise",
    "link": "https://www.competitions.co.nz/win-all-inclusive-asia-exploration-cruise/37721",
    "source": "Competitions.co.nz",
    "createdAt": "2025-11-11T03:41:55.479Z",
    "deadline": null,
    "tags": []
  },
  {
    "id": "https://www.competitions.co.nz/win-5k-visa-gift-card-months-supply-v-energy-drink/37720",
    "title": "Win $2.5K Visa Gift Card & a Month's Supply of V Energy Drink",
    "link": "https://www.competitions.co.nz/win-5k-visa-gift-card-months-supply-v-energy-drink/37720",
    "source": "Competitions.co.nz",
    "createdAt": "2025-11-11T03:41:55.479Z",
    "deadline": null,
    "tags": []
  },
  {
    "id": "https://www.competitions.co.nz/win-hekate-by-nikita-gill/37714",
    "title": "Win a copy of Hekate by Nikita Gill",
    "link": "https://www.competitions.co.nz/win-hekate-by-nikita-gill/37714",
    "source": "Competitions.co.nz",
    "createdAt": "2025-11-11T03:41:55.479Z",
    "deadline": "2025-11-30T00:00:00.000Z",
    "tags": []
  },
  {
    "id": "https://www.cheapies.nz/node/53734",
    "title": "Win 1 of 2 $500 Gift Cards from Smiggle",
    "link": "https://www.cheapies.nz/node/53734",
    "source": "cheapies.nz",
    "createdAt": "2025-11-10T19:48:21.000Z",
    "deadline": null,
    "tags": []
  },
  {
    "id": "https://www.cheapies.nz/node/53731",
    "title": "Win a Roomba Max 705 Combo Robot + AutoWash Dock from iRobot",
    "link": "https://www.cheapies.nz/node/53731",
    "source": "cheapies.nz",
    "createdAt": "2025-11-10T09:54:24.000Z",
    "deadline": null,
    "tags": []
  },
  {
    "id": "https://www.cheapies.nz/node/53726",
    "title": "Win a Wallace Cotton Heirloom Sheet and Pillowcase Set from Sealy",
    "link": "https://www.cheapies.nz/node/53726",
    "source": "cheapies.nz",
    "createdAt": "2025-11-09T19:57:05.000Z",
    "deadline": null,
    "tags": []
  },
  {
    "id": "https://www.cheapies.nz/node/53722",
    "title": "Win a Copy of Monument Valley: The Trilogy for Nintendo Switch from Legendary Prizes",
    "link": "https://www.cheapies.nz/node/53722",
    "source": "cheapies.nz",
    "createdAt": "2025-11-09T10:23:50.000Z",
    "deadline": null,
    "tags": []
  },
  {
    "id": "https://www.cheapies.nz/node/53715",
    "title": "Win an $80 Gift Voucher from Biltong Plus",
    "link": "https://www.cheapies.nz/node/53715",
    "source": "cheapies.nz",
    "createdAt": "2025-11-08T19:49:36.000Z",
    "deadline": null,
    "tags": []
  },
  {
    "id": "https://www.cheapies.nz/node/53714",
    "title": "Win a $25 Amazon Gift Card (Penalty Kiss Deal of The Week Giveaway) from Book Throne",
    "link": "https://www.cheapies.nz/node/53714",
    "source": "cheapies.nz",
    "createdAt": "2025-11-08T18:44:05.000Z",
    "deadline": null,
    "tags": []
  },
  {
    "id": "https://www.cheapies.nz/node/53713",
    "title": "Win a Copy of Hell Is Us for Xbox Series X from Legendary Prizes",
    "link": "https://www.cheapies.nz/node/53713",
    "source": "cheapies.nz",
    "createdAt": "2025-11-08T11:28:15.000Z",
    "deadline": null,
    "tags": []
  },
  {
    "id": "https://www.cheapies.nz/node/53707",
    "title": "Win a Copy of The Elder Scrolls IV: Oblivion Remastered for PS5 from Legendary Prizes",
    "link": "https://www.cheapies.nz/node/53707",
    "source": "cheapies.nz",
    "createdAt": "2025-11-07T19:44:33.000Z",
    "deadline": null,
    "tags": []
  },
  {
    "id": "https://www.cheapies.nz/node/53695",
    "title": "Win The Petite Vault (Worth $725) from Petite Skin Co",
    "link": "https://www.cheapies.nz/node/53695",
    "source": "cheapies.nz",
    "createdAt": "2025-11-06T19:52:01.000Z",
    "deadline": null,
    "tags": []
  },
  {
    "id": "https://www.cheapies.nz/node/53693",
    "title": "Win a Samsung Jet 65 Cordless Vacuum from Noel Leeming",
    "link": "https://www.cheapies.nz/node/53693",
    "source": "cheapies.nz",
    "createdAt": "2025-11-06T09:44:39.000Z",
    "deadline": null,
    "tags": []
  },
  {
    "id": "https://nzmcd.co.nz/competitions/win-1-of-5-beyou-muscle-joint-patches-sets",
    "title": "Win! 1 of 5 BeYou Muscle & Joint Patches sets",
    "link": "https://nzmcd.co.nz/competitions/win-1-of-5-beyou-muscle-joint-patches-sets",
    "source": "NZMCD",
    "createdAt": "2025-10-31T01:08:17.000Z",
    "deadline": null,
    "tags": []
  },
  {
    "id": "https://nzmcd.co.nz/competitions/win-1-of-5-rhino-guard-hitch-covers",
    "title": "Win! 1 of 5 Rhino Guard Hitch Covers",
    "link": "https://nzmcd.co.nz/competitions/win-1-of-5-rhino-guard-hitch-covers",
    "source": "NZMCD",
    "createdAt": "2025-10-31T00:56:13.000Z",
    "deadline": null,
    "tags": []
  },
  {
    "id": "https://nzmcd.co.nz/competitions/win-1-of-5-fend-insect-repellent-prize-packs",
    "title": "Win! 1 of 5 Fend Insect Repellent prize packs",
    "link": "https://nzmcd.co.nz/competitions/win-1-of-5-fend-insect-repellent-prize-packs",
    "source": "NZMCD",
    "createdAt": "2025-10-31T00:50:48.000Z",
    "deadline": null,
    "tags": []
  },
  {
    "id": "https://nzmcd.co.nz/competitions/win-1-of-5-roses-chilli-crisp-gift-packs",
    "title": "Win! 1 of 5 Rose’s Chilli Crisp gift packs",
    "link": "https://nzmcd.co.nz/competitions/win-1-of-5-roses-chilli-crisp-gift-packs",
    "source": "NZMCD",
    "createdAt": "2025-10-30T19:45:22.000Z",
    "deadline": null,
    "tags": []
  },
  {
    "id": "https://nzmcd.co.nz/competitions/win-a-kaleo-prize-pack",
    "title": "Win! a Kaleo prize pack",
    "link": "https://nzmcd.co.nz/competitions/win-a-kaleo-prize-pack",
    "source": "NZMCD",
    "createdAt": "2025-10-30T19:41:17.000Z",
    "deadline": null,
    "tags": []
  },
  {
    "id": "https://nzmcd.co.nz/competitions/win-aerial-art",
    "title": "Win! Aerial Art",
    "link": "https://nzmcd.co.nz/competitions/win-aerial-art",
    "source": "NZMCD",
    "createdAt": "2025-10-30T19:32:30.000Z",
    "deadline": null,
    "tags": []
  },
  {
    "id": "https://nzmcd.co.nz/competitions/win-necks-best-thing-pillow",
    "title": "Win! Neck’s Best Thing pillow",
    "link": "https://nzmcd.co.nz/competitions/win-necks-best-thing-pillow",
    "source": "NZMCD",
    "createdAt": "2025-10-30T19:28:39.000Z",
    "deadline": null,
    "tags": []
  },
  {
    "id": "https://nzmcd.co.nz/competitions/win-do-not-disturb-sleep-pack",
    "title": "Win! Do Not Disturb sleep pack",
    "link": "https://nzmcd.co.nz/competitions/win-do-not-disturb-sleep-pack",
    "source": "NZMCD",
    "createdAt": "2025-10-30T18:58:55.000Z",
    "deadline": null,
    "tags": []
  },
  {
    "id": "https://nzmcd.co.nz/competitions/win-1-of-2-fujifilm-quicksnap-cameras",
    "title": "Win! 1 of 2 FUJIFILM QuickSnap cameras",
    "link": "https://nzmcd.co.nz/competitions/win-1-of-2-fujifilm-quicksnap-cameras",
    "source": "NZMCD",
    "createdAt": "2025-09-06T01:20:18.000Z",
    "deadline": null,
    "tags": []
  },
  {
    "id": "https://nzmcd.co.nz/competitions/win-philips-festavia-hue-string-lights",
    "title": "Win! Philips Festavia Hue String Lights",
    "link": "https://nzmcd.co.nz/competitions/win-philips-festavia-hue-string-lights",
    "source": "NZMCD",
    "createdAt": "2025-09-06T01:12:06.000Z",
    "deadline": null,
    "tags": []
  },
  {
    "id": "https://nzmcd.co.nz/competitions/win-1-of-3-apostle-hot-sauce-gift-packs",
    "title": "Win! 1 of 3 Apostle Hot Sauce gift packs",
    "link": "https://nzmcd.co.nz/competitions/win-1-of-3-apostle-hot-sauce-gift-packs",
    "source": "NZMCD",
    "createdAt": "2025-09-05T23:21:23.000Z",
    "deadline": null,
    "tags": []
  },
  {
    "id": "https://nzmcd.co.nz/competitions/win-a-goodbugs-tastebud-teaser-box",
    "title": "Win! a GoodBugs Tastebud Teaser Box",
    "link": "https://nzmcd.co.nz/competitions/win-a-goodbugs-tastebud-teaser-box",
    "source": "NZMCD",
    "createdAt": "2025-09-05T23:11:18.000Z",
    "deadline": null,
    "tags": []
  }
]