{
  "startedAt": "2026-07-16T05:30:16.104Z",
  "finishedAt": "2026-07-16T05:31:41.003Z",
  "pulledAtIso": "2026-07-16T05:31:41.003Z",
  "counts": {
    "raw": 146,
    "normalized": 146,
    "deduped": 1139,
    "kept": 1074
  },
  "sources": {
    "rssCount": 4,
    "siteCount": 4,
    "rss": {
      "https://contest.co.nz/syndication.php?fid=2&limit=151": {
        "items": 50
      },
      "https://contest.co.nz/syndication.php?fid=13&limit=15": {
        "items": 15
      },
      "https://contest.co.nz/syndication.php?fid=14&limit=15": {
        "items": 15
      },
      "https://www.cheapies.nz/competition/all/feed": {
        "items": 10
      }
    },
    "sites": {
      "nzmcd.co.nz": {
        "items": 11,
        "indexed": 12,
        "pages": 1
      },
      "nowtolove.co.nz": {
        "items": 0,
        "indexed": 0,
        "pages": 1
      },
      "competitions.co.nz": {
        "items": 40,
        "indexed": 40,
        "pages": 3
      },
      "familytimes.co.nz": {
        "items": 5,
        "indexed": 6,
        "pages": 1
      }
    }
  },
  "perSource": {
    "competitions.co.nz": 262,
    "cheapies.nz": 357,
    "familytimes.co.nz": 12,
    "contest.co.nz": 407,
    "nzmcd.co.nz": 36
  }
}